include_file/__init__.py
include_file/__main__.py
include_file/models.py
include_file-0.0.20.dist-info/LICENSE
include_file-0.0.20.dist-info/METADATA
include_file-0.0.20.dist-info/WHEEL
include_file-0.0.20.dist-info/top_level.txt
include_file-0.0.20.dist-info/RECORD
