Metadata-Version: 2.1
Name: include-file
Version: 0.0.20
Summary: Replace {% include 'file.txt' %} with actual file contents
Home-page: https://github.com/seanhwangg/incluce_file
Author: Sean Hwang
Author-email: rbtmd1010@gmail.com
License: MIT
Platform: UNKNOWN
Requires-Python: >=3.8
License-File: LICENSE
Requires-Dist: beautifulsoup4 (==4.9.3)
Requires-Dist: bs4 (==0.0.1)
Requires-Dist: flake8 (==3.9.2)
Requires-Dist: Markdown (==3.3.4)
Requires-Dist: mccabe (==0.6.1)
Requires-Dist: mypy (==0.910)
Requires-Dist: mypy-extensions (==0.4.3)
Requires-Dist: pycodestyle (==2.7.0)
Requires-Dist: pyflakes (==2.3.1)
Requires-Dist: soupsieve (==2.2.1)
Requires-Dist: toml (==0.10.2)
Requires-Dist: typing-extensions (==3.10.0.0)
Requires-Dist: yapf (==0.31.0)
